{"devicePlatform":"","logFolder":"C:\\Users\\Claudio\\Katalon Studio\\TelepassTest\\Reports\\TestSuite1\\20180102_180144","runData":{"hostName":"Claudio - ASUS-HOME.lan","os":"Windows 10 64bit","katalonVersion":"5.2.0.1","browser":"Chrome 63.0.3239.84","hostAddress":"192.168.1.80","sessionId":"766cebc93b794e945cdd025b023bc93e","seleniumVersion":"3.7.1","proxyInformation":"ProxyInformation{proxyOption\u003dNO_PROXY, proxyServerType\u003dHTTP, password\u003d, proxyServerAddress\u003d, proxyServerPort\u003d0}","platform":"Windows 10"},"type":"TEST_SUITE","name":"TestSuite1","id":"Test Suites/TestSuite1","source":"","message":"Test Cases/NRT/TC_01_LoginOk","description":"","startTime":1514912511456,"endTime":1514912546461,"childRecords":[{"isOptional":false,"type":"TEST_CASE","name":"Test Cases/NRT/TC_01_LoginOk","id":"Test Cases/NRT/TC_01_LoginOk","source":"C:\\\\Users\\\\Claudio\\\\Katalon Studio\\\\TelepassTestTest Cases\\\\NRT\\\\TC_01_LoginOk.tc","message":"Test Cases/NRT/TC_01_LoginOk","description":"Verifica il corretto comportamento della funzionalit\\u00E0 di login","startTime":1514912512243,"endTime":1514912546368,"childRecords":[{"testStatus":{"stackTrace":"","statusValue":"INFO"},"type":"MESSAGE","name":"","message":"Evaluating variables for test case","startTime":1514912512660,"endTime":0,"childRecords":[],"interuppted":false},{"index":1,"isIgnoredIfFailed":false,"type":"TEST_STEP","name":"callTestCase","message":"Call Test Case \u0027Test Cases/FunzioniBase/fNavigaHomePage\u0027 successfully","description":"","startTime":1514912513456,"endTime":1514912531953,"childRecords":[{"isOptional":false,"type":"TEST_CASE","name":"Test Cases/FunzioniBase/fNavigaHomePage","id":"Test Cases/FunzioniBase/fNavigaHomePage","source":"C:\\\\Users\\\\Claudio\\\\Katalon Studio\\\\TelepassTestTest Cases\\\\FunzioniBase\\\\fNavigaHomePage.tc","message":"Test Cases/FunzioniBase/fNavigaHomePage","description":"","startTime":1514912513705,"endTime":1514912531936,"childRecords":[{"testStatus":{"stackTrace":"","statusValue":"INFO"},"type":"MESSAGE","name":"","message":"Evaluating variables for test case","startTime":1514912513733,"endTime":0,"childRecords":[],"interuppted":false},{"index":1,"isIgnoredIfFailed":false,"type":"TEST_STEP","name":"openBrowser","message":"Browser is opened with url: \u0027\u0027","description":"","startTime":1514912514206,"endTime":1514912521171,"childRecords":[{"testStatus":{"stackTrace":"","statusValue":"PASSED"},"type":"MESSAGE","name":"","message":"Browser is opened with url: \u0027\u0027","startTime":1514912521168,"endTime":0,"childRecords":[],"interuppted":false}],"interuppted":false},{"index":2,"isIgnoredIfFailed":false,"type":"TEST_STEP","name":"navigateToUrl","message":"Navigate to \u0027http://www.telepass.it\u0027 successfully","description":"","startTime":1514912521172,"endTime":1514912531770,"childRecords":[{"testStatus":{"stackTrace":"","statusValue":"PASSED"},"type":"MESSAGE","name":"","message":"Navigate to \u0027http://www.telepass.it\u0027 successfully","startTime":1514912531767,"endTime":0,"childRecords":[],"interuppted":false}],"interuppted":false},{"index":3,"isIgnoredIfFailed":false,"type":"TEST_STEP","name":"switchToWindowTitle","message":"Switched to window with title: \u0027Telepass: la soluzione di pagamento per la tua mobilità\u0027","description":"","startTime":1514912531771,"endTime":1514912531932,"childRecords":[{"testStatus":{"stackTrace":"","statusValue":"PASSED"},"type":"MESSAGE","name":"","message":"Switched to window with title: \u0027Telepass: la soluzione di pagamento per la tua mobilità\u0027","startTime":1514912531928,"endTime":0,"childRecords":[],"interuppted":false}],"interuppted":false},{"testStatus":{"stackTrace":"","statusValue":"PASSED"},"type":"MESSAGE","name":"","message":"Test Cases/FunzioniBase/fNavigaHomePage","startTime":1514912531932,"endTime":0,"childRecords":[],"interuppted":false}],"interuppted":false},{"testStatus":{"stackTrace":"","statusValue":"PASSED"},"type":"MESSAGE","name":"","message":"Call Test Case \u0027Test Cases/FunzioniBase/fNavigaHomePage\u0027 successfully","startTime":1514912531951,"endTime":0,"childRecords":[],"interuppted":false}],"interuppted":false},{"index":2,"isIgnoredIfFailed":false,"type":"TEST_STEP","name":"callTestCase","message":"Call Test Case \u0027Test Cases/FunzioniBase/fLogin\u0027 successfully","description":"","startTime":1514912531954,"endTime":1514912545058,"childRecords":[{"isOptional":false,"type":"TEST_CASE","name":"Test Cases/FunzioniBase/fLogin","id":"Test Cases/FunzioniBase/fLogin","source":"C:\\\\Users\\\\Claudio\\\\Katalon Studio\\\\TelepassTestTest Cases\\\\FunzioniBase\\\\fLogin.tc","message":"Test Cases/FunzioniBase/fLogin","description":"","startTime":1514912532030,"endTime":1514912545052,"childRecords":[{"testStatus":{"stackTrace":"","statusValue":"INFO"},"type":"MESSAGE","name":"","message":"Evaluating variables for test case","startTime":1514912532063,"endTime":0,"childRecords":[],"interuppted":false},{"testStatus":{"stackTrace":"","statusValue":"INFO"},"type":"MESSAGE","name":"","message":"Variable \u0027pUsername\u0027 is set to cgaiani","startTime":1514912532063,"endTime":0,"childRecords":[],"interuppted":false},{"testStatus":{"stackTrace":"","statusValue":"INFO"},"type":"MESSAGE","name":"","message":"Variable \u0027pPassword\u0027 is set to ********","startTime":1514912532067,"endTime":0,"childRecords":[],"interuppted":false},{"index":1,"isIgnoredIfFailed":false,"type":"TEST_STEP","name":"click","message":"Object: \u0027Object Repository/Page_Telepass la soluzione di pagam/span_Accedi\u0027 is clicked on","description":"","startTime":1514912532407,"endTime":1514912534419,"childRecords":[{"testStatus":{"stackTrace":"","statusValue":"PASSED"},"type":"MESSAGE","name":"","message":"Object: \u0027Object Repository/Page_Telepass la soluzione di pagam/span_Accedi\u0027 is clicked on","startTime":1514912534417,"endTime":0,"childRecords":[],"interuppted":false}],"interuppted":false},{"index":2,"isIgnoredIfFailed":false,"type":"TEST_STEP","name":"setText","message":"Text \u0027cgaiani\u0027 is set on object \u0027Object Repository/Page_Telepass.it - ACCEDI A TELEPAS/input_username\u0027","description":"","startTime":1514912534419,"endTime":1514912534913,"childRecords":[{"testStatus":{"stackTrace":"","statusValue":"PASSED"},"type":"MESSAGE","name":"","message":"Text \u0027cgaiani\u0027 is set on object \u0027Object Repository/Page_Telepass.it - ACCEDI A TELEPAS/input_username\u0027","startTime":1514912534909,"endTime":0,"childRecords":[],"interuppted":false}],"interuppted":false},{"index":3,"isIgnoredIfFailed":false,"type":"TEST_STEP","name":"setText","message":"Text \u0027alice123\u0027 is set on object \u0027Object Repository/Page_Telepass.it - ACCEDI A TELEPAS/input_password\u0027","description":"","startTime":1514912534914,"endTime":1514912535312,"childRecords":[{"testStatus":{"stackTrace":"","statusValue":"PASSED"},"type":"MESSAGE","name":"","message":"Text \u0027alice123\u0027 is set on object \u0027Object Repository/Page_Telepass.it - ACCEDI A TELEPAS/input_password\u0027","startTime":1514912535310,"endTime":0,"childRecords":[],"interuppted":false}],"interuppted":false},{"index":4,"isIgnoredIfFailed":false,"type":"TEST_STEP","name":"click","message":"Object: \u0027Object Repository/Page_Telepass.it - ACCEDI A TELEPAS/button_ACCEDI\u0027 is clicked on","description":"","startTime":1514912535313,"endTime":1514912545051,"childRecords":[{"testStatus":{"stackTrace":"","statusValue":"PASSED"},"type":"MESSAGE","name":"","message":"Object: \u0027Object Repository/Page_Telepass.it - ACCEDI A TELEPAS/button_ACCEDI\u0027 is clicked on","startTime":1514912545050,"endTime":0,"childRecords":[],"interuppted":false}],"interuppted":false},{"testStatus":{"stackTrace":"","statusValue":"PASSED"},"type":"MESSAGE","name":"","message":"Test Cases/FunzioniBase/fLogin","startTime":1514912545052,"endTime":0,"childRecords":[],"interuppted":false}],"interuppted":false},{"testStatus":{"stackTrace":"","statusValue":"PASSED"},"type":"MESSAGE","name":"","message":"Call Test Case \u0027Test Cases/FunzioniBase/fLogin\u0027 successfully","startTime":1514912545052,"endTime":0,"childRecords":[],"interuppted":false}],"interuppted":false},{"index":3,"isIgnoredIfFailed":false,"type":"TEST_STEP","name":"verifyElementText","message":"Actual text and expected text of test object \u0027Object Repository/Page_Telepass.it Telepass S.p.A./span_CLAUDIO GAIANI\u0027 are matched.","description":"","startTime":1514912545059,"endTime":1514912545274,"childRecords":[{"testStatus":{"stackTrace":"","statusValue":"PASSED"},"type":"MESSAGE","name":"","message":"Actual text and expected text of test object \u0027Object Repository/Page_Telepass.it Telepass S.p.A./span_CLAUDIO GAIANI\u0027 are matched.","startTime":1514912545274,"endTime":0,"childRecords":[],"interuppted":false}],"interuppted":false},{"index":4,"isIgnoredIfFailed":false,"type":"TEST_STEP","name":"closeBrowser","message":"Browser is closed","description":"","startTime":1514912545274,"endTime":1514912546366,"childRecords":[{"testStatus":{"stackTrace":"","statusValue":"PASSED"},"type":"MESSAGE","name":"","message":"Browser is closed","startTime":1514912546361,"endTime":0,"childRecords":[],"interuppted":false}],"interuppted":false},{"testStatus":{"stackTrace":"","statusValue":"PASSED"},"type":"MESSAGE","name":"","message":"Test Cases/NRT/TC_01_LoginOk","startTime":1514912546367,"endTime":0,"childRecords":[],"interuppted":false}],"interuppted":false}],"interuppted":false}